pantherdb/__init__.py
pantherdb/pantherdb.py
pantherdb-2.3.3.dist-info/licenses/LICENSE
pantherdb-2.3.3.dist-info/METADATA
pantherdb-2.3.3.dist-info/WHEEL
pantherdb-2.3.3.dist-info/top_level.txt
pantherdb-2.3.3.dist-info/RECORD
