Metadata-Version: 2.4
Name: pantherdb
Version: 2.3.3
Summary: is a Simple, FileBase and Document Oriented database
Home-page: https://github.com/PantherPy/pantherdb
Author: Ali RajabNezhad
Author-email: alirn76@yahoo.com
License: MIT
Classifier: Operating System :: OS Independent
Classifier: License :: OSI Approved :: MIT License
Classifier: Programming Language :: Python :: 3.8
Classifier: Programming Language :: Python :: 3.9
Classifier: Programming Language :: Python :: 3.10
Classifier: Programming Language :: Python :: 3.11
Classifier: Programming Language :: Python :: 3.12
Classifier: Programming Language :: Python :: 3.13
Classifier: Programming Language :: Python :: 3.14
Requires-Python: >=3.8
License-File: LICENSE
Requires-Dist: orjson~=3.11.3
Requires-Dist: simple-ulid~=1.0.0
Provides-Extra: full
Requires-Dist: cryptography~=41.0; extra == "full"
Dynamic: author
Dynamic: author-email
Dynamic: classifier
Dynamic: description
Dynamic: description-content-type
Dynamic: home-page
Dynamic: license
Dynamic: license-file
Dynamic: provides-extra
Dynamic: requires-dist
Dynamic: requires-python
Dynamic: summary
